dr_captcha/__init__.py
dr_captcha/captcha.py
dr_captcha/captcha_py2.png
dr_captcha/captcha_py3.png
dr_captcha/fonts/COPYRIGHT.TXT
dr_captcha/fonts/README.TXT
dr_captcha/fonts/Vera.ttf
dr_captcha/serializers.py
dr_captcha/settings.py
dr_captcha/tests.py
dr_captcha/urls.py
dr_captcha/utils.py
dr_captcha/views.py
dr_captcha-1.0.0.dist-info/LICENSE
dr_captcha-1.0.0.dist-info/METADATA
dr_captcha-1.0.0.dist-info/WHEEL
dr_captcha-1.0.0.dist-info/RECORD
