Metadata-Version: 2.1
Name: dr-captcha
Version: 1.0.0
Summary: fork from django-rest-captcha for work with django-rest-framework and support for new django versions
License: MIT
Author: evgeny.zuev
Author-email: zueves@gmail.com
Classifier: License :: OSI Approved :: MIT License
Classifier: Programming Language :: Python :: 2
Classifier: Programming Language :: Python :: 2.7
Classifier: Programming Language :: Python :: 3
Classifier: Programming Language :: Python :: 3.4
Classifier: Programming Language :: Python :: 3.5
Classifier: Programming Language :: Python :: 3.6
Classifier: Programming Language :: Python :: 3.7
Classifier: Programming Language :: Python :: 3.8
Classifier: Programming Language :: Python :: 3.9
Classifier: Programming Language :: Python :: 3.10
Classifier: Programming Language :: Python :: 3.11
Requires-Dist: Pillow (>=4.3.0)
Requires-Dist: django
Requires-Dist: djangorestframework (>=3.5,<4.0)
